terminalchate/__init__.py
terminalchate/_version.py
terminalchate/client.py
terminalchate/core.py
terminalchate/server.py
terminalchate-0.1.3.dist-info/licenses/LICENSE
terminalchate-0.1.3.dist-info/METADATA
terminalchate-0.1.3.dist-info/WHEEL
terminalchate-0.1.3.dist-info/entry_points.txt
terminalchate-0.1.3.dist-info/top_level.txt
terminalchate-0.1.3.dist-info/RECORD
