Metadata-Version: 2.4
Name: terminalchate
Version: 0.1.3
Summary: Tiny terminal chat: async TCP server + CLI client
Author: Enver Celik
License: MIT License
Project-URL: Homepage, https://github.com/EnverDev/terminalchat
Project-URL: Issues, https://github.com/EnverDev/terminalchat/issues
Keywords: chat,asyncio,terminal,tcp
Classifier: Programming Language :: Python :: 3
Classifier: Programming Language :: Python :: 3.13
Classifier: License :: OSI Approved :: MIT License
Classifier: Operating System :: OS Independent
Classifier: Topic :: Communications :: Chat
Requires-Python: >=3.13
License-File: LICENSE
Dynamic: license-file
